pingdomlib/__init__.py
pingdomlib/analysis.py
pingdomlib/check.py
pingdomlib/contact.py
pingdomlib/pingdom.py
pingdomlib/reports.py
PingdomLib3-3.0.0.dist-info/LICENSE.txt
PingdomLib3-3.0.0.dist-info/METADATA
PingdomLib3-3.0.0.dist-info/WHEEL
PingdomLib3-3.0.0.dist-info/top_level.txt
PingdomLib3-3.0.0.dist-info/RECORD
