Metadata-Version: 2.1
Name: PingdomLib3
Version: 3.0.0
Summary: A documented python library to consume the full pingdom API
Home-page: https://github.com/NovaTec-APM/PingdomLib
Author: Mario Mann
Author-email: dedi-extern@novatec-gmbh.de
License: ISC license
Platform: UNKNOWN
Classifier: Programming Language :: Python :: 3
Classifier: Development Status :: 5 - Production/Stable
Classifier: Intended Audience :: Developers
Classifier: Intended Audience :: System Administrators
Classifier: License :: OSI Approved :: ISC License (ISCL)
Classifier: Operating System :: OS Independent
Classifier: Topic :: System :: Monitoring
Requires-Dist: requests (>=2.2.1)
